scoda_viz-0.4.30.dist-info/licenses/LICENSE
scodaviz/__init__.py
scodaviz/load_data.py
scodaviz/misc.py
scodaviz/pl.py
scodaviz/pl_py312.py
scodaviz/supp.py
scodaviz/data/surfaceome_genes.txt
scoda_viz-0.4.30.dist-info/METADATA
scoda_viz-0.4.30.dist-info/WHEEL
scoda_viz-0.4.30.dist-info/entry_points.txt
scoda_viz-0.4.30.dist-info/top_level.txt
scoda_viz-0.4.30.dist-info/RECORD
