Metadata-Version: 2.4
Name: scoda-viz
Version: 0.4.30
Summary: Visualization Toolkits for SCODA results.
Author-email: Seokhyun Yoon <syoon@dku.edu>
License:                     GNU GENERAL PUBLIC LICENSE
Project-URL: Homepage, https://github.com/combio-dku
Keywords: single-cell omics,bioinformatics
Classifier: Programming Language :: Python
Classifier: Programming Language :: Python :: 3
License-File: LICENSE
Provides-Extra: dev
Requires-Dist: numpy; extra == "dev"
Requires-Dist: pandas; extra == "dev"
Requires-Dist: scipy; extra == "dev"
Requires-Dist: scikit-learn; extra == "dev"
Requires-Dist: scikit-network; extra == "dev"
Dynamic: license-file
